
{"header" : {
  "cloc_url"           : "github.com/AlDanial/cloc",
  "cloc_version"       : "1.90",
  "elapsed_seconds"    : 2.0760190486908,
  "n_files"            : 124,
  "n_lines"            : 11509,
  "files_per_second"   : 59.7297024216605,
  "lines_per_second"   : 5543.78342879751},
"JavaScript" :{
  "nFiles": 107,
  "blank": 1244,
  "comment": 246,
  "code": 9115},
"JSON" :{
  "nFiles": 6,
  "blank": 1,
  "comment": 0,
  "code": 552},
"CSS" :{
  "nFiles": 9,
  "blank": 43,
  "comment": 36,
  "code": 229},
"Markdown" :{
  "nFiles": 1,
  "blank": 9,
  "comment": 0,
  "code": 25},
"XML" :{
  "nFiles": 1,
  "blank": 0,
  "comment": 0,
  "code": 9},
"SUM": {
  "blank": 1297,
  "comment": 282,
  "code": 9930,
  "nFiles": 124} }
